sampleScript/__init__.py
sampleScript/script.py
setupDefaultTest-0.0.0.dist-info/DESCRIPTION.rst
setupDefaultTest-0.0.0.dist-info/METADATA
setupDefaultTest-0.0.0.dist-info/RECORD
setupDefaultTest-0.0.0.dist-info/WHEEL
setupDefaultTest-0.0.0.dist-info/metadata.json
setupDefaultTest-0.0.0.dist-info/top_level.txt
