Metadata-Version: 2.0
Name: setupDefaultTest
Version: 0.0.0
Summary: A log writer function for py based docker containers.
Home-page: UNKNOWN
Author: 
Author-email: 
License: UNKNOWN
Platform: UNKNOWN
Requires-Python: ~=3.6
